ais2gpd/__init__.py
ais2gpd/core.py
ais2gpd-1.0.5.dist-info/LICENSE
ais2gpd-1.0.5.dist-info/WHEEL
ais2gpd-1.0.5.dist-info/METADATA
ais2gpd-1.0.5.dist-info/RECORD
